{"themeConfig":{"footer":{"copyright":"Copyright © 2012-present Zammad Foundation","message":"Zammad Hub"},"nav":[{"link":"https://www.zammad.com","text":"Zammad.com"},{"link":"https://community.zammad.org/","text":"Community forum"}],"sidebar":[{"items":[{"items":[{"link":"get-started/start","text":"Start"},{"link":"get-started/deployment","text":"Deyploy Zammad"}],"text":"Get Zammad"}],"text":"Get started with Zammad"},{"items":[{"collapsed":true,"items":[{"link":"/documentation/user-docs/index","text":"Login"},{"link":"/documentation/user-docs/index","text":"Ticket handling"}],"text":"Use Zammad"},{"collapsed":true,"items":[{"link":"/documentation/user-docs/index","text":"General settings"},{"link":"/documentation/user-docs/index","text":"User management"}],"text":"Administrate Zammad"}],"text":"Dokumentation"},{"items":[{"link":"contribute/style-and-content-guide","text":"Style and content guide"},{"link":"contribute/contribute","text":"Contribution"}],"text":"Contribute"},{"items":[{"link":"reference/glossary","text":"Glossary"},{"link":"reference/api-reference","text":"API reference"},{"link":"reference/rails-commands","text":"Rails commands"}],"text":"Reference"},{"items":[{"link":"/documentation/admin-docs/index","text":"Admin documentation"},{"link":"/cheat-sheet","text":"Formatting cheat sheet"}],"text":"Playground (example content)"}],"socialLinks":[{"icon":"github","link":"https://github.com/zammad"}]}}
